shadowray/__init__.py
shadowray/common/B64.py
shadowray/common/__init__.py
shadowray/common/utils.py
shadowray/config/__init__.py
shadowray/config/v2_repo.py
shadowray/config/v2ray.py
shadowray/config/version.py
shadowray/core/__init__.py
shadowray/core/configuration.py
shadowray/core/execute.py
shadowray/core/manager.py
shadowray/core/server.py
shadowray/subscribe/__init__.py
shadowray/subscribe/parser.py
shadowray-0.1.6.dist-info/LICENSE
shadowray-0.1.6.dist-info/METADATA
shadowray-0.1.6.dist-info/WHEEL
shadowray-0.1.6.dist-info/entry_points.txt
shadowray-0.1.6.dist-info/top_level.txt
shadowray-0.1.6.dist-info/RECORD
